labelprop/DataLoading.py
labelprop/MultiLevelNet.py
labelprop/Pretraining_model.py
labelprop/__init__.py
labelprop/api.py
labelprop/cli.py
labelprop/conf.json
labelprop/lightning_model.py
labelprop/napari_entry.py
labelprop/train.py
labelprop/utils.py
labelprop/voxelmorph2d.py
labelprop/weight_optimizer.py
deep_labelprop-1.2.3.dist-info/LICENSE
deep_labelprop-1.2.3.dist-info/METADATA
deep_labelprop-1.2.3.dist-info/WHEEL
deep_labelprop-1.2.3.dist-info/entry_points.txt
deep_labelprop-1.2.3.dist-info/top_level.txt
deep_labelprop-1.2.3.dist-info/RECORD
