Metadata-Version: 2.1
Name: deep-labelprop
Version: 1.2.3
Summary: Label propagation using deep registration
Home-page: https://github.com/nathandecaux/labelprop
Author: Nathan Decaux
Author-email: nathan.decaux@imt-atlantique.fr
License: MIT license
Keywords: labelprop
Classifier: Development Status :: 2 - Pre-Alpha
Classifier: Intended Audience :: Developers
Classifier: License :: OSI Approved :: MIT License
Classifier: Natural Language :: English
Classifier: Programming Language :: Python :: 3
Classifier: Programming Language :: Python :: 3.6
Classifier: Programming Language :: Python :: 3.7
Classifier: Programming Language :: Python :: 3.8
Requires-Python: >=3.8
License-File: LICENSE
Requires-Dist: Flask >=2.1.0
Requires-Dist: kornia >=0.6.12
Requires-Dist: monai >=1.1
Requires-Dist: nibabel >=3.2.1
Requires-Dist: numpy
Requires-Dist: plotext >=4.2.0
Requires-Dist: lightning
Requires-Dist: torchvision
Requires-Dist: pandas
